ropt/__init__.py
ropt/enums.py
ropt/exceptions.py
ropt/py.typed
ropt/version.py
ropt/config/__init__.py
ropt/config/_enopt_config.py
ropt/config/_function_estimator_config.py
ropt/config/_gradient_config.py
ropt/config/_linear_constraints_config.py
ropt/config/_nonlinear_constraints_config.py
ropt/config/_objective_functions_config.py
ropt/config/_optimizer_config.py
ropt/config/_realization_filter_config.py
ropt/config/_realizations_config.py
ropt/config/_sampler_config.py
ropt/config/_variables_config.py
ropt/config/constants.py
ropt/config/options.py
ropt/config/utils.py
ropt/config/validated_types.py
ropt/ensemble_evaluator/__init__.py
ropt/ensemble_evaluator/_ensemble_evaluator.py
ropt/ensemble_evaluator/_evaluator_results.py
ropt/ensemble_evaluator/_function.py
ropt/ensemble_evaluator/_gradient.py
ropt/ensemble_evaluator/_utils.py
ropt/evaluator/__init__.py
ropt/evaluator/_evaluator.py
ropt/optimization/__init__.py
ropt/optimization/_callback.py
ropt/optimization/_optimizer.py
ropt/plan/__init__.py
ropt/plan/_basic_optimizer.py
ropt/plan/_events.py
ropt/plan/_plan.py
ropt/plugins/__init__.py
ropt/plugins/_manager.py
ropt/plugins/base.py
ropt/plugins/function_estimator/__init__.py
ropt/plugins/function_estimator/base.py
ropt/plugins/function_estimator/default.py
ropt/plugins/optimizer/__init__.py
ropt/plugins/optimizer/base.py
ropt/plugins/optimizer/external.py
ropt/plugins/optimizer/scipy.py
ropt/plugins/optimizer/utils.py
ropt/plugins/plan/__init__.py
ropt/plugins/plan/_function_evaluator.py
ropt/plugins/plan/_observer.py
ropt/plugins/plan/_store.py
ropt/plugins/plan/_tracker.py
ropt/plugins/plan/_utils.py
ropt/plugins/plan/base.py
ropt/plugins/plan/cached_evaluator.py
ropt/plugins/plan/default.py
ropt/plugins/plan/ensemble_evaluator.py
ropt/plugins/plan/optimizer.py
ropt/plugins/realization_filter/__init__.py
ropt/plugins/realization_filter/base.py
ropt/plugins/realization_filter/default.py
ropt/plugins/sampler/__init__.py
ropt/plugins/sampler/base.py
ropt-0.24.1.dist-info/licenses/LICENSE
ropt-0.24.1.dist-info/METADATA
ropt-0.24.1.dist-info/WHEEL
ropt-0.24.1.dist-info/entry_points.txt
ropt-0.24.1.dist-info/top_level.txt
ropt-0.24.1.dist-info/RECORD
