Metadata-Version: 2.4
Name: ropt
Version: 0.24.1
Summary: The ropt ensemble optimizer module
Project-URL: Homepage, https://github.com/TNO-ropt/ropt
Project-URL: Repository, https://github.com/TNO-ropt/ropt
Project-URL: Bug Tracker, https://github.com/TNO-ropt/ropt/issues
Project-URL: Documentation, https://tno-ropt.github.io/ropt
Classifier: Development Status :: 4 - Beta
Classifier: License :: OSI Approved :: GNU General Public License v3 (GPLv3)
Classifier: Natural Language :: English
Classifier: Programming Language :: Python
Classifier: Programming Language :: Python :: 3.11
Classifier: Programming Language :: Python :: 3.12
Classifier: Programming Language :: Python :: 3.13
Classifier: Programming Language :: Python :: 3.14
Classifier: Topic :: Scientific/Engineering
Requires-Python: >=3.11
License-File: LICENSE
Requires-Dist: numpy
Requires-Dist: pydantic
Requires-Dist: scipy>=1.15
Provides-Extra: pandas
Requires-Dist: pandas; extra == "pandas"
Dynamic: license-file
